openlog/__init__.py
openlog/config.toml
openlog/logger.py
openlog/core/__init__.py
openlog/core/batch.py
openlog/core/file_handler.py
openlog/core/formatter.py
openlog/core/object_formatter.py
openlog/core/task_manager.py
openlog/core/text_wrapper.py
openlog/core/timestamp.py
openlog-2.1.0.dist-info/licenses/LICENSE
openlog-2.1.0.dist-info/METADATA
openlog-2.1.0.dist-info/WHEEL
openlog-2.1.0.dist-info/top_level.txt
openlog-2.1.0.dist-info/RECORD
