Metadata-Version: 2.4
Name: openlog
Version: 2.1.0
Summary: Open-source minimal Rich-based logging solution
Author-email: Hexerpowers <hexerpowers@gmail.com>
License-Expression: MIT
Project-URL: Homepage, https://github.com/Hexerpowers/openlog
Keywords: logs,file-logging
Classifier: Programming Language :: Python
Classifier: Programming Language :: Python :: 3
Requires-Python: >=3.9
License-File: LICENSE
Requires-Dist: rich
Requires-Dist: setuptools>=68
Requires-Dist: tomli>=2.2.1
Requires-Dist: tomli; python_version < "3.11"
Requires-Dist: wheel>=0.45.1
Provides-Extra: dev
Requires-Dist: black; extra == "dev"
Requires-Dist: bumpver; extra == "dev"
Requires-Dist: isort; extra == "dev"
Requires-Dist: pip-tools; extra == "dev"
Requires-Dist: pytest; extra == "dev"
Dynamic: license-file
